aws_scheduler/__init__.py
aws_scheduler/kernel/__init__.py
aws_scheduler/kernel/scheduler.py
aws_scheduler/kernel/schema.py
aws_scheduler-1.0.0.dist-info/LICENSE
aws_scheduler-1.0.0.dist-info/METADATA
aws_scheduler-1.0.0.dist-info/WHEEL
aws_scheduler-1.0.0.dist-info/top_level.txt
aws_scheduler-1.0.0.dist-info/RECORD
