Metadata-Version: 2.1
Name: aws-scheduler
Version: 1.0.0
Summary: This package makes it easy to manage Glue Crawler and Cloudwatch schedulers on AWS services. You can schedule lambda function execution, etc.
Home-page: https://github.com/da-huin/aws_scheduler
Author: JunYeong Park
Author-email: dahuin000@gmail.com
License: MIT
Download-URL: https://github.com/da-huin/aws_scheduler/archive/master.zip
Platform: UNKNOWN
Classifier: Programming Language :: Python :: 3
Requires-Dist: boto3
Requires-Dist: template-manager
